Bessel/BesselFilter.py
Bessel/__init__.py
Butterworth/ButterworthFilter.py
Butterworth/__init__.py
Cauer/CauerFilter.py
Cauer/__init__.py
Chebyshev/ChebyshevFilter.py
Chebyshev/__init__.py
Gaussian/FSG.py
Gaussian/FspecialGauss.py
Gaussian/GaussianFilter.py
Gaussian/GaussianKernel.py
Gaussian/__init__.py
Kalman/KalmanFilter.py
Kalman/__init__.py
FilterUtils-2.0.0.dist-info/METADATA
FilterUtils-2.0.0.dist-info/WHEEL
FilterUtils-2.0.0.dist-info/top_level.txt
FilterUtils-2.0.0.dist-info/RECORD
