Metadata-Version: 2.1
Name: FilterUtils
Version: 2.0.0
Summary: A Python library for various filters
Author: Jarvis
Author-email: Jarvis@ldsb.com
License: MIT
Classifier: Development Status :: 3 - Alpha
Classifier: Intended Audience :: Developers
Classifier: License :: OSI Approved :: MIT License
Classifier: Programming Language :: Python :: 3
Classifier: Programming Language :: Python :: 3.6
Classifier: Programming Language :: Python :: 3.7
Classifier: Programming Language :: Python :: 3.8
